checkedid/__init__.py
checkedid/client.py
checkedid/endpoints.py
checkedid/errors.py
checkedid/models/__init__.py
checkedid/models/base.py
checkedid/models/generated.py
checkedid/models/missing.py
checkedid/models/renamed.py
checkedid/py.typed
checkedid-0.4.0.dist-info/METADATA
checkedid-0.4.0.dist-info/WHEEL
checkedid-0.4.0.dist-info/LICENSE
checkedid-0.4.0.dist-info/RECORD
